pyspal/__init__.py
pyspal/img_coder.py
pyspal/pyspal.py
pyspal-0.0.1.dist-info/LICENSE
pyspal-0.0.1.dist-info/METADATA
pyspal-0.0.1.dist-info/WHEEL
pyspal-0.0.1.dist-info/top_level.txt
pyspal-0.0.1.dist-info/RECORD
