Metadata-Version: 2.1
Name: pyspal
Version: 0.0.1
Summary: A 2D game engine for python that is incredibly easy to use and that has a many tools.
Author: Perfogy
Author-email: <perfogyofficial@gmail.com>
Keywords: python,game engine,2d,games,game,perfogy
Classifier: Development Status :: 1 - Planning
Classifier: Intended Audience :: Developers
Classifier: Programming Language :: Python :: 3
Classifier: Operating System :: Unix
Classifier: Operating System :: MacOS :: MacOS X
Classifier: Operating System :: Microsoft :: Windows
License-File: LICENSE
Requires-Dist: pygame
